setup.py
vsionailibs/__init__.py
vsionailibs/imageops.py
vsionailibs.egg-info/PKG-INFO
vsionailibs.egg-info/SOURCES.txt
vsionailibs.egg-info/dependency_links.txt
vsionailibs.egg-info/not-zip-safe
vsionailibs.egg-info/requires.txt
vsionailibs.egg-info/top_level.txt