Metadata-Version: 1.0
Name: vsionailibs
Version: 1.0.1
Summary: the public libs of vsion.ai
Home-page: https://git.tech.rz.db.de/ZhenyuGeng/vsion-ai-libs.git
Author: Zhenyu Geng
Author-email: zhenyu.geng@deutschebahn.com
License: MIT
Platform: UNKNOWN
